autospec/__main__.py
autospec/data_converter.py
autospec/goniometer_view.py
autospec/plotter.py
autospec/spectralon_corrector.py
autospec/verticalscrolledframe.py
autospec/global_config/color_config.mplstyle
autospec/global_config/size_config.mplstyle
AutoSpec-0.1.4.dist-info/METADATA
AutoSpec-0.1.4.dist-info/WHEEL
AutoSpec-0.1.4.dist-info/top_level.txt
AutoSpec-0.1.4.dist-info/RECORD
