Metadata-Version: 2.1
Name: AutoSpec
Version: 0.1.4
Summary: Control software for spectroscopy using ASD RS3 and ViewSpec Pro
Home-page: https://github.com/kathleenhoza/autospectroscopy
Author: Kathleen Hoza
Author-email: kathleenhoza@gmail.com
License: Creative Commons Attribution-Noncommercial-Share Alike license
Platform: UNKNOWN
Requires-Python: >=3
Requires-Dist: pygame
Requires-Dist: matplotlib
Requires-Dist: numpy
Requires-Dist: cython
Requires-Dist: colorutils
